mosaicx/__init__.py
mosaicx/__main__.py
mosaicx/constants.py
mosaicx/display.py
mosaicx/document_loader.py
mosaicx/extractor.py
mosaicx/mosaicx.py
mosaicx/standardizer.py
mosaicx/summarizer.py
mosaicx/text_extraction.py
mosaicx/api/__init__.py
mosaicx/api/extraction.py
mosaicx/api/schema.py
mosaicx/api/summary.py
mosaicx/cli/__init__.py
mosaicx/cli/app.py
mosaicx/schema/__init__.py
mosaicx/schema/builder.py
mosaicx/schema/registry.py
mosaicx/schema/templates/__init__.py
mosaicx/schema/templates/json/__init__.py
mosaicx/schema/templates/python/__init__.py
mosaicx/schema/templates/python/echocontractv01_extract_patient_number_20251009_190202.py
mosaicx/schema/templates/python/patient_identity.py
mosaicx/utils/__init__.py
mosaicx/utils/config.py
mosaicx/utils/pathing.py
mosaicx-1.1.1.dist-info/METADATA
mosaicx-1.1.1.dist-info/WHEEL
mosaicx-1.1.1.dist-info/entry_points.txt
mosaicx-1.1.1.dist-info/licenses/LICENSE
mosaicx-1.1.1.dist-info/RECORD
