Metadata-Version: 2.4
Name: mosaicx
Version: 1.1.1
Summary: Medical cOmputational Suite for Advanced Intelligent eXtraction
Project-URL: Homepage, https://github.com/LalithShiyam/MOSAICX
Project-URL: Repository, https://github.com/LalithShiyam/MOSAICX
Project-URL: Documentation, https://github.com/LalithShiyam/MOSAICX#readme
Project-URL: Bug Tracker, https://github.com/LalithShiyam/MOSAICX/issues
Author-email: Lalith Kumar Shiyam Sundar <lalith.shiyam@med.uni-muenchen.de>
License:                                  Apache License
License-File: LICENSE
Keywords: extraction,llm,medical,nlp,pdf,radiology
Classifier: Development Status :: 5 - Production/Stable
Classifier: Intended Audience :: Healthcare Industry
Classifier: Intended Audience :: Science/Research
Classifier: License :: OSI Approved :: Apache Software License
Classifier: Programming Language :: Python :: 3
Classifier: Programming Language :: Python :: 3.11
Classifier: Programming Language :: Python :: 3.12
Classifier: Topic :: Scientific/Engineering :: Medical Science Apps.
Classifier: Topic :: Text Processing :: Linguistic
Requires-Python: >=3.11
Requires-Dist: click>=8.1.0
Requires-Dist: docling>=2.0.0
Requires-Dist: dspy-ai>=2.4.0
Requires-Dist: httpx>=0.25.0
Requires-Dist: instructor>=1.0.0
Requires-Dist: ollama>=0.3.0
Requires-Dist: openai>=1.0.0
Requires-Dist: pydantic>=2.0.0
Requires-Dist: python-cfonts>=1.0.0
Requires-Dist: pyyaml>=6.0
Requires-Dist: reportlab>=4.4.4
Requires-Dist: requests>=2.31.0
Requires-Dist: rich-click>=1.8.0
Requires-Dist: rich>=13.0.0
Requires-Dist: typing-extensions>=4.8.0
Provides-Extra: dev
Requires-Dist: black>=23.7.0; extra == 'dev'
Requires-Dist: isort>=5.12.0; extra == 'dev'
Requires-Dist: mypy>=1.5.0; extra == 'dev'
Requires-Dist: pre-commit>=3.3.0; extra == 'dev'
Requires-Dist: pytest-asyncio>=0.21.0; extra == 'dev'
Requires-Dist: pytest-cov>=4.1.0; extra == 'dev'
Requires-Dist: pytest>=7.4.0; extra == 'dev'
Requires-Dist: ruff>=0.0.280; extra == 'dev'
